altair_upset/__init__.py
altair_upset/components.py
altair_upset/config.py
altair_upset/preprocessing.py
altair_upset/transforms.py
altair_upset/upset.py
altair_upset-0.5.0.dist-info/METADATA
altair_upset-0.5.0.dist-info/WHEEL
altair_upset-0.5.0.dist-info/licenses/LICENSE
altair_upset-0.5.0.dist-info/RECORD
