Metadata-Version: 2.4
Name: altair-upset
Version: 0.5.0
Summary: Create interactive UpSet plots using Altair
Project-URL: Homepage, https://github.com/edmundmiller/altair-upset
Project-URL: Documentation, https://altair-upset.readthedocs.io
Project-URL: Repository, https://github.com/edmundmiller/altair-upset.git
Project-URL: Issues, https://github.com/edmundmiller/altair-upset/issues
Author-email: Edmund Miller <git@edmundmiller.dev>
License: MIT
License-File: LICENSE
Keywords: altair,sets,upset,vega,visualization
Classifier: Development Status :: 4 - Beta
Classifier: Intended Audience :: Science/Research
Classifier: License :: OSI Approved :: MIT License
Classifier: Programming Language :: Python :: 3
Classifier: Programming Language :: Python :: 3.9
Classifier: Programming Language :: Python :: 3.10
Classifier: Programming Language :: Python :: 3.11
Classifier: Topic :: Scientific/Engineering :: Visualization
Requires-Python: <4,>=3.9
Requires-Dist: altair<6.0.0,>=5.0.0
Requires-Dist: pandas<3.0.0,>=2.0.0
